mlx.coverity-2.0.3-py3.9-nspkg.pth
mlx/coverity/__coverity_version__.py
mlx/coverity/__init__.py
mlx/coverity/coverity.py
mlx/coverity/coverity_item_element.py
mlx/coverity/coverity_services.py
mlx/coverity/coverity_directives/__init__.py
mlx/coverity/coverity_directives/coverity_defect_list.py
mlx.coverity-2.0.3.dist-info/LICENSE
mlx.coverity-2.0.3.dist-info/METADATA
mlx.coverity-2.0.3.dist-info/WHEEL
mlx.coverity-2.0.3.dist-info/namespace_packages.txt
mlx.coverity-2.0.3.dist-info/top_level.txt
mlx.coverity-2.0.3.dist-info/RECORD
