Metadata-Version: 2.1
Name: mlx.coverity
Version: 2.0.3
Summary: Sphinx coverity extension from Melexis
Home-page: https://github.com/melexis/sphinx-coverity-extension
Author: Crt Mori
Author-email: cmo@melexis.com
License: GNU General Public License v3 (GPLv3)
Keywords: coverity,reporting,reStructuredText coverity report,sphinx,ASPICE,ISO26262,ASIL
Platform: any
Classifier: Development Status :: 5 - Production/Stable
Classifier: Environment :: Console
Classifier: Environment :: Web Environment
Classifier: Framework :: Sphinx :: Extension
Classifier: Intended Audience :: Developers
Classifier: License :: OSI Approved :: GNU General Public License v3 (GPLv3)
Classifier: Operating System :: OS Independent
Classifier: Programming Language :: Python
Classifier: Programming Language :: Python :: 3.8
Classifier: Programming Language :: Python :: 3.9
Classifier: Programming Language :: Python :: 3.10
Classifier: Programming Language :: Python :: 3.11
Classifier: Programming Language :: Python :: 3.12
Classifier: Topic :: Documentation
Classifier: Topic :: Documentation :: Sphinx
Classifier: Topic :: Utilities
Requires-Python: >=3.8
License-File: LICENSE
Requires-Dist: Sphinx >=2.1
Requires-Dist: docutils
Requires-Dist: setuptools-scm
Requires-Dist: matplotlib
Requires-Dist: mlx.traceability
Requires-Dist: urlextract
